pollboy/__init__.py
pollboy/config.py
pollboy/db.py
pollboy/logger.py
pollboy/pollboy.py
pollboy/settings.py
pollboy/notifiers/__init__.py
pollboy/notifiers/mailersend.py
pollboy/notifiers/smtp.py
pollboy/notifiers/telegram.py
pollboy-0.4.0.dist-info/METADATA
pollboy-0.4.0.dist-info/WHEEL
pollboy-0.4.0.dist-info/entry_points.txt
pollboy-0.4.0.dist-info/top_level.txt
pollboy-0.4.0.dist-info/RECORD
